LICENSE
MANIFEST.in
README.md
setup.py
astutils/__init__.py
astutils/_version.py
astutils/ast.py
astutils/ply.py
astutils.egg-info/PKG-INFO
astutils.egg-info/SOURCES.txt
astutils.egg-info/dependency_links.txt
astutils.egg-info/requires.txt
astutils.egg-info/top_level.txt
examples/README.md
examples/setup.py
examples/foo/__init__.py
examples/foo/ast.py
examples/foo/backend.py
examples/foo/lexyacc.py
tests/ast_test.py
tests/ply_test.py