Metadata-Version: 1.1
Name: astutils
Version: 0.0.3
Summary: Utilities for abstract syntax trees and parsing with PLY.
Home-page: https://github.com/johnyf/astutils
Author: Ioannis Filippidis
Author-email: jfilippidis@gmail.com
License: BSD
Keywords: lexing,parsing,syntax tree,abstract syntax tree,AST,PLY,lex,yacc
Platform: UNKNOWN
Classifier: Development Status :: 2 - Pre-Alpha
Classifier: Intended Audience :: Developers
Classifier: License :: OSI Approved :: BSD License
Classifier: Operating System :: OS Independent
Classifier: Programming Language :: Python
Classifier: Programming Language :: Python :: 2.7
Classifier: Programming Language :: Python :: 3
Classifier: Programming Language :: Python :: 3.4
Classifier: Programming Language :: Python :: 3.5
Classifier: Programming Language :: Python :: 3.6
Classifier: Topic :: Software Development
